{"cameraMode":{"drawMode":0,"name":"Shaded","section":"Shading Mode"},"sceneLighting":true,"audioPlay":false,"sceneViewState":{"m_AlwaysRefresh":false,"showFog":true,"showSkybox":true,"showFlares":true,"showImageEffects":true,"showParticleSystems":true,"showVisualEffectGraphs":true,"m_FxEnabled":true},"in2DMode":false,"pivot":{"x":-25.376399993896486,"y":-2.7951138019561769,"z":1.4353348016738892},"rotation":{"x":-0.14341697096824647,"y":0.7018682360649109,"z":-0.1476292908191681,"w":-0.681946873664856},"size":3.1038668155670168,"orthographic":false}